animsprite_pygame/__init__.py
animsprite_pygame/spritesheet.py
animsprite_pygame/version.py
animsprite_pygame/__pycache__/__init__.cpython-314.pyc
animsprite_pygame/__pycache__/spritesheet.cpython-314.pyc
animsprite_pygame/__pycache__/version.cpython-314.pyc
animsprite_pygame-0.2.1.dist-info/licenses/LICENSE
animsprite_pygame-0.2.1.dist-info/METADATA
animsprite_pygame-0.2.1.dist-info/WHEEL
animsprite_pygame-0.2.1.dist-info/top_level.txt
animsprite_pygame-0.2.1.dist-info/RECORD
