Metadata-Version: 2.4
Name: animsprite-pygame
Version: 0.2.1
Summary: Une librairie légère pour gérer les spritesheets et flipbooks dans Pygame
Home-page: https://github.com/EnOx-S/animsprite-pygame
Author: EnOx_S
Author-email: EnOxS_Off <enoxs.pro@gmail.com>
License: GPL-3.0-only
Project-URL: Homepage, https://github.com/EnOx-S/animsprite-pygame
Project-URL: Bug Tracker, https://github.com/EnOx-S/animsprite-pygame/issues
Project-URL: Documentation, https://github.com/EnOx-S/animsprite-pygame#readme
Project-URL: Source Code, https://github.com/EnOx-S/animsprite-pygame
Keywords: pygame,sprite,animation,spritesheet,flipbook,game
Classifier: Development Status :: 3 - Alpha
Classifier: Intended Audience :: Developers
Classifier: Topic :: Software Development :: Libraries :: Python Modules
Classifier: Topic :: Multimedia :: Graphics
Classifier: License :: OSI Approved :: GNU General Public License v3 (GPLv3)
Classifier: Programming Language :: Python :: 3
Classifier: Programming Language :: Python :: 3.8
Classifier: Programming Language :: Python :: 3.9
Classifier: Programming Language :: Python :: 3.10
Classifier: Programming Language :: Python :: 3.11
Classifier: Programming Language :: Python :: 3.12
Classifier: Programming Language :: Python :: 3.13
Classifier: Programming Language :: Python :: 3.14
Classifier: Operating System :: OS Independent
Requires-Python: >=3.8
License-File: LICENSE
Requires-Dist: pygame-ce>=2.3.0
Provides-Extra: dev
Requires-Dist: pytest>=6.0; extra == "dev"
Requires-Dist: black>=21.0; extra == "dev"
Requires-Dist: flake8>=3.9; extra == "dev"
Requires-Dist: isort>=5.0; extra == "dev"
Dynamic: author
Dynamic: home-page
Dynamic: license-file
Dynamic: requires-python
